djangoanalytics/__init__.py
djangoanalytics/apps.py
djangoanalytics/auth.py
djangoanalytics/models.py
djangoanalytics/parser.py
djangoanalytics/process.py
djangoanalytics/querytool.py
djangoanalytics/tests.py
djangoanalytics/urls.py
djangoanalytics/views.py
djangoanalytics/behaviors/__init__.py
djangoanalytics/behaviors/agents.py
djangoanalytics/behaviors/hits.py
djangoanalytics/management/__init__.py
djangoanalytics/management/commands/__init__.py
djangoanalytics/management/commands/hitmanager.py
djangoanalytics/migrations/0001_initial.py
djangoanalytics/migrations/0002_auto_20190208_1453.py
djangoanalytics/migrations/0003_auto_20190212_1257.py
djangoanalytics/migrations/0004_auto_20190212_1258.py
djangoanalytics/migrations/0005_auto_20190212_1324.py
djangoanalytics/migrations/0006_auto_20190212_1504.py
djangoanalytics/migrations/__init__.py
finxi_djangoanalytics-0.1.13.dist-info/LICENSE
finxi_djangoanalytics-0.1.13.dist-info/METADATA
finxi_djangoanalytics-0.1.13.dist-info/WHEEL
finxi_djangoanalytics-0.1.13.dist-info/top_level.txt
finxi_djangoanalytics-0.1.13.dist-info/RECORD
